bball/__init__.py
bball/models.py
bball/utils.py
bball-0.1.2.dist-info/METADATA
bball-0.1.2.dist-info/WHEEL
bball-0.1.2.dist-info/RECORD
