Metadata-Version: 2.4
Name: bball
Version: 0.1.2
Summary: NBA analytics platform with core models and utilities
Project-URL: Homepage, https://bball.dev
Project-URL: Documentation, https://docs.bball.dev
Project-URL: Repository, https://github.com/bball-dev/bball
Project-URL: Issues, https://github.com/bball-dev/bball/issues
Author-email: Nicholas Cooper <nicholascullencooper@gmail.com>
Keywords: analytics,basketball,data,nba,sports
Requires-Python: >=3.13
Requires-Dist: httpx>=0.27
Requires-Dist: numpy>=1.26
Requires-Dist: pandas>=2.2
Requires-Dist: pydantic>=2.9
Provides-Extra: all
Requires-Dist: bball-api>=0.1.0; extra == 'all'
Requires-Dist: bball-cli>=0.1.0; extra == 'all'
Requires-Dist: bball-data>=0.1.0; extra == 'all'
Requires-Dist: bball-reports>=0.1.0; extra == 'all'
Requires-Dist: bball-strategies>=0.1.0; extra == 'all'
Provides-Extra: analytics
Requires-Dist: bball-data>=0.1.0; extra == 'analytics'
Requires-Dist: bball-reports>=0.1.0; extra == 'analytics'
Requires-Dist: bball-strategies>=0.1.0; extra == 'analytics'
Provides-Extra: api
Requires-Dist: bball-api>=0.1.0; extra == 'api'
Provides-Extra: cli
Requires-Dist: bball-cli>=0.1.0; extra == 'cli'
Provides-Extra: data
Requires-Dist: bball-data>=0.1.0; extra == 'data'
Provides-Extra: reports
Requires-Dist: bball-reports>=0.1.0; extra == 'reports'
Provides-Extra: strategies
Requires-Dist: bball-strategies>=0.1.0; extra == 'strategies'
Provides-Extra: web
Requires-Dist: bball-api>=0.1.0; extra == 'web'
